pyjquants/__init__.py
pyjquants/py.typed
pyjquants/adapters/__init__.py
pyjquants/adapters/endpoints.py
pyjquants/domain/__init__.py
pyjquants/domain/base.py
pyjquants/domain/futures.py
pyjquants/domain/index.py
pyjquants/domain/info.py
pyjquants/domain/market.py
pyjquants/domain/options.py
pyjquants/domain/ticker.py
pyjquants/domain/utils.py
pyjquants/domain/models/__init__.py
pyjquants/domain/models/base.py
pyjquants/domain/models/company.py
pyjquants/domain/models/derivatives.py
pyjquants/domain/models/financial.py
pyjquants/domain/models/market.py
pyjquants/domain/models/price.py
pyjquants/infra/__init__.py
pyjquants/infra/cache.py
pyjquants/infra/client.py
pyjquants/infra/config.py
pyjquants/infra/decorators.py
pyjquants/infra/exceptions.py
pyjquants/infra/session.py
pyjquants-0.3.0.dist-info/METADATA
pyjquants-0.3.0.dist-info/WHEEL
pyjquants-0.3.0.dist-info/licenses/LICENSE
pyjquants-0.3.0.dist-info/RECORD
