Metadata-Version: 2.4
Name: pyjquants
Version: 0.3.0
Summary: Investor-friendly OOP Python library for J-Quants API
Project-URL: Homepage, https://github.com/obichan117/pyjquants
Project-URL: Documentation, https://github.com/obichan117/pyjquants#readme
Project-URL: Repository, https://github.com/obichan117/pyjquants.git
Author: obichan117
License-Expression: MIT
License-File: LICENSE
Keywords: api,finance,japan,jquants,stock,trading
Classifier: Development Status :: 3 - Alpha
Classifier: Intended Audience :: Developers
Classifier: Intended Audience :: Financial and Insurance Industry
Classifier: License :: OSI Approved :: MIT License
Classifier: Operating System :: OS Independent
Classifier: Programming Language :: Python :: 3
Classifier: Programming Language :: Python :: 3.10
Classifier: Programming Language :: Python :: 3.11
Classifier: Programming Language :: Python :: 3.12
Classifier: Topic :: Office/Business :: Financial :: Investment
Classifier: Typing :: Typed
Requires-Python: >=3.10
Requires-Dist: pandas>=2.0
Requires-Dist: pydantic>=2.0
Requires-Dist: python-dateutil>=2.8
Requires-Dist: requests>=2.31
Provides-Extra: all
Requires-Dist: aiohttp>=3.9; extra == 'all'
Requires-Dist: diskcache>=5.6; extra == 'all'
Provides-Extra: async
Requires-Dist: aiohttp>=3.9; extra == 'async'
Provides-Extra: cache
Requires-Dist: diskcache>=5.6; extra == 'cache'
Provides-Extra: dev
Requires-Dist: aiohttp>=3.9; extra == 'dev'
Requires-Dist: mkdocs-jupyter>=0.24; extra == 'dev'
Requires-Dist: mkdocs-material>=9.5; extra == 'dev'
Requires-Dist: mkdocs-static-i18n>=1.2; extra == 'dev'
Requires-Dist: mkdocs>=1.5; extra == 'dev'
Requires-Dist: mkdocstrings[python]>=0.24; extra == 'dev'
Requires-Dist: mypy>=1.0; extra == 'dev'
Requires-Dist: pandas-stubs; extra == 'dev'
Requires-Dist: pytest-asyncio>=0.21; extra == 'dev'
Requires-Dist: pytest-cov>=4.0; extra == 'dev'
Requires-Dist: pytest>=7.0; extra == 'dev'
Requires-Dist: ruff>=0.1; extra == 'dev'
Requires-Dist: tomli>=2.0; extra == 'dev'
Requires-Dist: types-requests; extra == 'dev'
